bjtube/__init__.py
bjtube/main.py
bjtube-1.0.4.dist-info/METADATA
bjtube-1.0.4.dist-info/WHEEL
bjtube-1.0.4.dist-info/entry_points.txt
bjtube-1.0.4.dist-info/top_level.txt
bjtube-1.0.4.dist-info/RECORD
