Metadata-Version: 2.4
Name: bjtube
Version: 1.0.4
Summary: 🎬 YouTube downloader with faster speed, ffmpeg is essential to use before installation. with auto-update and dependency installer by Babar Ali Jamali.
Home-page: https://github.com/babaralijamali/bjtube
Author: Babar Ali Jamali
Author-email: babar995@gmail.com
Requires-Python: >=3.7
Requires-Dist: tqdm
Requires-Dist: colorama
Dynamic: author
Dynamic: author-email
Dynamic: description
Dynamic: description-content-type
Dynamic: home-page
Dynamic: requires-dist
Dynamic: requires-python
Dynamic: summary
